highlightjs/__init__.py
highlightjs/models.py
highlightjs/renderer.py
highlightjs/settings.py
highlightjs/templatetags/__init__.py
highlightjs/templatetags/highlightjs.py
django_highlightjs-0.2.14.dist-info/AUTHORS.md
django_highlightjs-0.2.14.dist-info/LICENSE
django_highlightjs-0.2.14.dist-info/METADATA
django_highlightjs-0.2.14.dist-info/WHEEL
django_highlightjs-0.2.14.dist-info/RECORD
