Metadata-Version: 2.3
Name: django-highlightjs
Version: 0.2.14
Summary: A Django app to easyily integrate highlight.js syntax highlighter.
License: MIT
Keywords: django,highlightjs,syntax,highlighter,syntax highlighter,highlight.js
Author: Mounir Messelmeni
Author-email: messelmeni.mounir@gmail.com
Requires-Python: >=3.10,<3.14
Classifier: Development Status :: 4 - Beta
Classifier: Environment :: Web Environment
Classifier: Framework :: Django
Classifier: Framework :: Django :: 4.2
Classifier: Framework :: Django :: 5.0
Classifier: Framework :: Django :: 5.1
Classifier: Intended Audience :: Developers
Classifier: License :: OSI Approved :: MIT License
Classifier: Operating System :: OS Independent
Classifier: Programming Language :: Python
Classifier: Programming Language :: Python :: 3
Classifier: Programming Language :: Python :: 3.10
Classifier: Programming Language :: Python :: 3.11
Classifier: Programming Language :: Python :: 3.12
Classifier: Programming Language :: Python :: 3.13
Classifier: Topic :: Software Development :: Libraries :: Python Modules
Requires-Dist: Django (>=4.2)
Project-URL: Homepage, https://github.com/mounirmesselmeni/django-highlightjs/
Project-URL: Repository, https://github.com/mounirmesselmeni/django-highlightjs/
